README.md
pyproject.toml
fairo/__init__.py
fairo/settings.py
fairo.egg-info/PKG-INFO
fairo.egg-info/SOURCES.txt
fairo.egg-info/dependency_links.txt
fairo.egg-info/requires.txt
fairo.egg-info/top_level.txt
fairo/core/__init__.py
fairo/core/exceptions.py
fairo/core/utils.py
fairo/core/agent/__init__.py
fairo/core/agent/base_agent.py
fairo/core/agent/code_analysis_agent.py
fairo/core/agent/utils.py
fairo/core/agent/output/__init__.py
fairo/core/agent/output/base_output.py
fairo/core/agent/output/google_drive.py
fairo/core/agent/tools/__init__.py
fairo/core/agent/tools/base_tools.py
fairo/core/agent/tools/code_analysis.py
fairo/core/agent/tools/utils.py
fairo/core/chat/__init__.py
fairo/core/chat/chat.py
fairo/core/client/__init__.py
fairo/core/client/client.py
fairo/core/execution/__init__.py
fairo/core/execution/agent_serializer.py
fairo/core/execution/env_finder.py
fairo/core/execution/executor.py
fairo/core/execution/model_log_helper.py
fairo/core/models/__init__.py
fairo/core/models/custom_field_value.py
fairo/core/models/resources.py
fairo/core/runnable/__init__.py
fairo/core/runnable/runnable.py
fairo/core/tools/__init__.py
fairo/core/tools/plot.py
fairo/core/tools/suggestion.py
fairo/core/workflow/__init__.py
fairo/core/workflow/base_workflow.py
fairo/core/workflow/dependency.py
fairo/core/workflow/utils.py
fairo/metrics/__init__.py
fairo/metrics/fairness_object.py
fairo/metrics/metrics.py
fairo/tests/__init__.py
fairo/tests/test_metrics.py