Metadata-Version: 2.4
Name: fairo
Version: 26.1.1
Summary: SDK for interfacing with Fairo SaaS platform.
Author-email: "Fairo Systems, Inc." <support@fairo.ai>
License: Apache-2.0
Project-URL: homepage, https://www.fairo.ai
Keywords: fairo,AI,agents,governance,fairness,metrics,security,compliance,risk
Classifier: Programming Language :: Python :: 3.9
Classifier: Programming Language :: Python :: 3.10
Classifier: License :: OSI Approved :: Apache Software License
Classifier: Operating System :: OS Independent
Requires-Dist: mlflow<=3.1.1,>=3.1.0
Requires-Dist: langchain<0.4.0,>=0.3.27
Requires-Dist: langchain-aws<0.3.0,>=0.2.18
Requires-Dist: langchain-community<0.4.0,>=0.3.27
Requires-Dist: langchain-core<0.4.0,>=0.3.49
Requires-Dist: langchain-text-splitters<0.4.0,>=0.3.11
Requires-Dist: setuptools>=79.0.0
Requires-Dist: pandas<3.0.0,>=2.0.0
